tests/__init__.py
tests/test_tree.py
treeit/__init__.py
treeit/tree.py
treeit-0.0.1.dist-info/LICENSE
treeit-0.0.1.dist-info/METADATA
treeit-0.0.1.dist-info/WHEEL
treeit-0.0.1.dist-info/top_level.txt
treeit-0.0.1.dist-info/RECORD
