Metadata-Version: 2.1
Name: treeit
Version: 0.0.1
Summary: tree like,like linux tree command
Home-page: https://github.com/xunull/treeit
Author: xunull
Author-email: xunull@163.com
License: UNKNOWN
Platform: UNKNOWN
Classifier: Programming Language :: Python :: 3
Classifier: License :: OSI Approved :: Apache Software License
Classifier: Operating System :: OS Independent
Requires-Python: >=3.0
